botable/__init__.py
botable/__main__.py
botable/common.py
botable/play.py
botable/py.typed
botable/record.py
botable-0.0.11.dist-info/licenses/LICENSE
botable-0.0.11.dist-info/METADATA
botable-0.0.11.dist-info/WHEEL
botable-0.0.11.dist-info/entry_points.txt
botable-0.0.11.dist-info/top_level.txt
botable-0.0.11.dist-info/RECORD
