Metadata-Version: 2.4
Name: botable
Version: 0.0.11
Summary: Record and play keyboard and mouse events
Home-page: http://github.com/ebonnal/botable
Author: Enzo Bonnal
Author-email: bonnal.enzo.dev@gmail.com
License: Apache 2.
License-File: LICENSE
Requires-Dist: pynput==1.7.7
Dynamic: author
Dynamic: author-email
Dynamic: description
Dynamic: description-content-type
Dynamic: home-page
Dynamic: license
Dynamic: license-file
Dynamic: requires-dist
Dynamic: summary
